inform/__init__.py
inform/__init__.pyi
inform/inform.py
inform/inform.pyi
inform/py.typed
inform-1.35.dist-info/licenses/LICENSE
inform-1.35.dist-info/WHEEL
inform-1.35.dist-info/METADATA
inform-1.35.dist-info/RECORD
