Metadata-Version: 2.4
Name: inform
Version: 1.35
Summary: print & logging utilities for communicating with user
Keywords: inform,logging,printing
Author: Ken Kundert
Author-email: inform@nurdletech.com
Requires-Python: >=3.6
Classifier: Development Status :: 5 - Production/Stable
Classifier: Intended Audience :: Developers
Classifier: License :: OSI Approved :: MIT License
Classifier: Natural Language :: English
Classifier: Operating System :: POSIX :: Linux
Classifier: Programming Language :: Python :: 3
Classifier: Topic :: Utilities
License-File: LICENSE
Requires-Dist: arrow
Requires-Dist: six
Requires-Dist: hypothesis ; extra == "test"
Requires-Dist: mypy ; extra == "test"
Requires-Dist: num2words ; extra == "test"
Requires-Dist: pylama ; extra == "test"
Requires-Dist: pytest ; extra == "test"
Requires-Dist: pytest-cov ; extra == "test"
Requires-Dist: quantiphy ; extra == "test"
Requires-Dist: tox ; extra == "test"
Project-URL: changelog, https://github.com/KenKundert/inform/blob/master/doc/releases.rst
Project-URL: documentation, https://inform.readthedocs.io
Project-URL: homepage, https://inform.readthedocs.io
Project-URL: repository, https://github.com/kenkundert/inform
Provides-Extra: test
